boatrace/__init__.py
boatrace/models/__init__.py
boatrace/models/betting_method.py
boatrace/models/branch.py
boatrace/models/disqualification.py
boatrace/models/gender.py
boatrace/models/motor_parts.py
boatrace/models/prefecture.py
boatrace/models/race_grade.py
boatrace/models/race_kind.py
boatrace/models/race_laps.py
boatrace/models/racer_rank.py
boatrace/models/stadium_tel_code.py
boatrace/models/weather.py
boatrace/models/winning_trick.py
boatrace.models-0.0.1.dist-info/LICENSE.txt
boatrace.models-0.0.1.dist-info/METADATA
boatrace.models-0.0.1.dist-info/WHEEL
boatrace.models-0.0.1.dist-info/top_level.txt
boatrace.models-0.0.1.dist-info/RECORD
